base_descriptor/__init__.py
base_descriptor/data_descriptor.py
base_descriptor/non_data_descriptor.py
base_descriptor/slottable_data_descriptor.py
base_descriptor-1.2.dist-info/LICENSE
base_descriptor-1.2.dist-info/METADATA
base_descriptor-1.2.dist-info/WHEEL
base_descriptor-1.2.dist-info/top_level.txt
base_descriptor-1.2.dist-info/RECORD
