Metadata-Version: 2.1
Name: base-descriptor
Version: 1.2
Summary: A simple, fast, typed, and tested abstract and base classes for a python3.6+ Non Data Descriptor, Data Descriptor, and Slottable Data Descriptor.
Home-page: https://github.com/tybruno/base-descriptor
Author: Tyler Bruno
License: MIT
Keywords: descriptor data-descriptor non-data-descriptor slottable-data-descriptor
Classifier: License :: OSI Approved :: MIT License
Classifier: Programming Language :: Python
Classifier: Programming Language :: Python :: 3.6
Classifier: Programming Language :: Python :: 3.7
Classifier: Programming Language :: Python :: 3.8
Classifier: Programming Language :: Python :: 3.9
Classifier: Programming Language :: Python :: 3.10
Classifier: Programming Language :: Python :: 3 :: Only
Classifier: Topic :: Software Development :: Libraries :: Python Modules
Requires-Python: >=3.6
License-File: LICENSE
